projpicker/VERSION
projpicker/__init__.py
projpicker/common.py
projpicker/coor_latlon.py
projpicker/coor_xy.py
projpicker/getosm.py
projpicker/gui.py
projpicker/gui_common.py
projpicker/gui_tk.py
projpicker/gui_wx.py
projpicker/projpicker.db
projpicker/projpicker.py
projpicker/wxpanel.py
projpicker/web/__init__.py
projpicker/web/index.html
projpicker/web/projpicker.css
projpicker/web/projpicker.js
projpicker/web/web.py
projpicker-0.3.2.dist-info/LICENSE
projpicker-0.3.2.dist-info/METADATA
projpicker-0.3.2.dist-info/WHEEL
projpicker-0.3.2.dist-info/entry_points.txt
projpicker-0.3.2.dist-info/top_level.txt
projpicker-0.3.2.dist-info/RECORD
