Metadata-Version: 2.1
Name: projpicker
Version: 0.3.2
Summary: ProjPicker (projection picker) allows the user to select all projections whose extent completely contains given points, polylines, polygons, and bounding boxes. The goal is to make it easy and visual to select a desired projection by location.
Home-page: https://github.com/HuidaeCho/projpicker
Author: Huidae Cho and Owen Smith
Author-email: grass4u@gmail.com
License: GPLv3+
Platform: UNKNOWN
Classifier: Programming Language :: Python :: 3
Classifier: License :: OSI Approved :: GNU General Public License v3 or later (GPLv3+)
Classifier: Operating System :: OS Independent
Requires-Python: >=3
License-File: LICENSE
